AUTHORS
LICENSE
MANIFEST.in
README.md
setup.py
csrc/flash_attn/fmha_api.cpp
csrc/flash_attn/src/fmha.h
csrc/flash_attn/src/fmha_block_dgrad_fp16_kernel_loop.sm80.cu
csrc/flash_attn/src/fmha_block_dgrad_kernel_1xN_loop.h
csrc/flash_attn/src/fmha_block_fprop_fp16_kernel.sm80.cu
csrc/flash_attn/src/fmha_block_fprop_kernel_1xN.h
csrc/flash_attn/src/fmha_blockmask.h
csrc/flash_attn/src/fmha_bwd_hdim128.cu
csrc/flash_attn/src/fmha_bwd_hdim32.cu
csrc/flash_attn/src/fmha_bwd_hdim64.cu
csrc/flash_attn/src/fmha_bwd_launch_template.h
csrc/flash_attn/src/fmha_dgrad_kernel_1xN_loop.h
csrc/flash_attn/src/fmha_fprop_kernel_1xN.h
csrc/flash_attn/src/fmha_fwd_hdim128.cu
csrc/flash_attn/src/fmha_fwd_hdim32.cu
csrc/flash_attn/src/fmha_fwd_hdim64.cu
csrc/flash_attn/src/fmha_fwd_launch_template.h
csrc/flash_attn/src/fmha_kernel.h
csrc/flash_attn/src/fmha_utils.h
csrc/flash_attn/src/philox.cuh
csrc/flash_attn/src/static_switch.h
csrc/flash_attn/src/fmha/gemm.h
csrc/flash_attn/src/fmha/gmem_tile.h
csrc/flash_attn/src/fmha/kernel_traits.h
csrc/flash_attn/src/fmha/mask.h
csrc/flash_attn/src/fmha/smem_tile.h
csrc/flash_attn/src/fmha/softmax.h
csrc/flash_attn/src/fmha/utils.h
csrc/ft_attention/cuda_bf16_fallbacks.cuh
csrc/ft_attention/cuda_bf16_wrapper.h
csrc/ft_attention/decoder_masked_multihead_attention.cu
csrc/ft_attention/decoder_masked_multihead_attention.h
csrc/ft_attention/decoder_masked_multihead_attention_utils.h
csrc/ft_attention/ft_attention.cpp
csrc/fused_dense_lib/fused_dense.cpp
csrc/fused_dense_lib/fused_dense_cuda.cu
csrc/fused_softmax/fused_softmax.cpp
csrc/fused_softmax/scaled_masked_softmax.h
csrc/fused_softmax/scaled_masked_softmax_cuda.cu
csrc/fused_softmax/scaled_upper_triang_masked_softmax.h
csrc/fused_softmax/scaled_upper_triang_masked_softmax_cuda.cu
csrc/fused_softmax/type_shim.h
csrc/layer_norm/ln.h
csrc/layer_norm/ln_api.cpp
csrc/layer_norm/ln_bwd_1024.cu
csrc/layer_norm/ln_bwd_1280.cu
csrc/layer_norm/ln_bwd_1536.cu
csrc/layer_norm/ln_bwd_2048.cu
flash_attn_wheels.egg-info/PKG-INFO
flash_attn_wheels.egg-info/SOURCES.txt
flash_attn_wheels.egg-info/dependency_links.txt
flash_attn_wheels.egg-info/requires.txt
flash_attn_wheels.egg-info/top_level.txt