Metadata-Version: 2.1
Name: flash-attn-wheels
Version: 1.0.9
Summary: Flash Attention: Fast and Memory-Efficient Exact Attention
Home-page: https://github.com/piercefreeman/flash-attention
Author: Pierce Freeman
Author-email: pierce@freeman.vc
Classifier: Programming Language :: Python :: 3
Classifier: License :: OSI Approved :: BSD License
Classifier: Operating System :: Unix
Requires-Python: >=3.7
License-File: LICENSE
License-File: AUTHORS
